best_of/__init__.py
best_of/_about.py
best_of/_cli.py
best_of/default_config.py
best_of/generator.py
best_of/license.py
best_of/projects_collection.py
best_of/utils.py
best_of/yaml_generation.py
best_of/generators/__init__.py
best_of/generators/base_generator.py
best_of/generators/markdown_list.py
best_of/integrations/__init__.py
best_of/integrations/base_integration.py
best_of/integrations/cargo_integration.py
best_of/integrations/conda_integration.py
best_of/integrations/dockerhub_integration.py
best_of/integrations/github_integration.py
best_of/integrations/gitlab_integration.py
best_of/integrations/go_integration.py
best_of/integrations/libio_integration.py
best_of/integrations/maven_integration.py
best_of/integrations/npm_integration.py
best_of/integrations/pypi_integration.py
best_of-0.8.6.dist-info/LICENSE
best_of-0.8.6.dist-info/METADATA
best_of-0.8.6.dist-info/WHEEL
best_of-0.8.6.dist-info/entry_points.txt
best_of-0.8.6.dist-info/top_level.txt
best_of-0.8.6.dist-info/RECORD
